{
  "name": "Perfect Draw!",
  "menuBackgroundImage": "https://img.itch.zone/aW1nLzE3MjYxMTQ3LnBuZw==/original/p1T42W.png",
  "defaultRessources": {
    "backgrounds": [],
    "decksUrl": ""
  },
  "customHelp": "",
  "cardRotation": 45,
  "cards": {
    "dataUrl": "https://raw.githubusercontent.com/edoardovoccia/Perfect-Draw-data/refs/heads/main/Perfect%20Draw%20Staples.json",
    "cardBack": "https://i.imgur.com/m5XiqFX.jpeg"
  },
  "deckBuilding": {
    "mainFilters": [
      "Staple",
      "Created Card"
    ],
    "formats": [
      {
        "title": "Standard",
        "gameplay": "Standard",
        "customCategories": [
          "Staple",
          "Main Deck",
          "Created Card"
        ],
        "sections": [
          {
            "title": "Staple",
            "categories": ["Staple"],
            "min": 0,
            "max": 100
          },
          {
            "title": "Main Deck",
            "categories": ["Main Deck"],
            "min": 0,
            "max": 100
          },
          {
            "title": "Created Card",
            "categories": ["Created Card"],
            "min": 0,
            "max": 100
          }
        ]
      }
    ]
  },
  "gameplay": {
    "Standard": {
      "mulligan": {
        "startingHandSize": 2,
        "drawNewHand": false,
        "putSelectionAtBottom": false,
        "drawNewSelectedCards": false
      },
      "newTurn": {
        "drawOnStart": false,
        "sharedTurn": false,
        "drawPerTurn": 0
      },
      "tokens": [
        {
          "name": "Weak Warrior",
          "image": "https://i.imgur.com/orojBLO.png"
        },
        {
          "name": "Normal Warrior",
          "image": "https://i.imgur.com/C7Kggmx.jpeg"
        },
        {
          "name": "Strong Warrior",
          "image": "https://i.imgur.com/HHWkmR7.png"
        }
      ],
      "countersStartingValues": [1],
      "sections": {
        "customSections": ["Battlefield"],
        "sectionsDict": {
          "Battlefield": {
            "title": "Battlefield",
            "height": "BIG",
            "alignment": "CENTER"
          }
        },
        "layout": {
          "direction": "row",
          "content": ["Battlefield"]
        },
        "categoriesAlreadyOnBoard": [],
        "autoPlayFromHand": {
          "Staple": "Battlefield",
          "Created Card": "Battlefield",
          "Main Deck": "Battlefield"
        }
      }
    }
  }
}
